{
    "content": {
        "rows": [
            {
                "config": {},
                "items": [
                    {
                        "title": "Blog",
                        "crumbs": [
                            {
                                "title": "",
                                "href": "#",
                                "label": "Home"
                            },
                            {
                                "title": "",
                                "href": "",
                                "label": "Blog"
                            }
                        ],
                        "_ref": "/parBreadcrumb"
                    }
                ]
            },
            {
                "config": {},
                "items": [
                    {
                        "blogs": {
                            "items": [
                                {
                                    "date": {
                                        "day": "23",
                                        "monthYear": "August, 2018"
                                    },
                                    "title": "SEO: The Movie By Ignite Visibility",
                                    "summary": "Lorem ipsum dolor sit amet, consetetur sadipscing esed diam nonumy eirmod tempor invidunt ut",
                                    "link": {
                                        "title": "",
                                        "href": "#",
                                        "label": "Read More"
                                    },
                                    "image": {
                                        "src": "/_client/images/bg-img/8.jpg",
                                        "alt": ""
                                    }
                                },
                                {
                                    "date": {
                                        "day": "13",
                                        "monthYear": "December, 2018"
                                    },
                                    "title": "What Curling Irons Are The Best Ones",
                                    "summary": "Lorem ipsum dolor sit amet, consetetur sadipscing esed diam nonumy eirmod tempor invidunt ut",
                                    "link": {
                                        "label": "Read More",
                                        "href": "#",
                                        "title": ""
                                    },
                                    "image": {
                                        "src": "/_client/images/bg-img/9.jpg",
                                        "alt": ""
                                    }
                                },
                                {
                                    "date": {
                                        "day": "08",
                                        "monthYear": "July, 2018"
                                    },
                                    "title": "Amazon REV Workshop: Road to Seattle",
                                    "summary": "Lorem ipsum dolor sit amet, consetetur sadipscing esed diam nonumy eirmod tempor invidunt ut",
                                    "link": {
                                        "label": "Read more",
                                        "href": "#",
                                        "title": ""
                                    },
                                    "image": {
                                        "src": "/_client/images/bg-img/10.jpg",
                                        "alt": ""
                                    }
                                }
                            ],
                            "_ref": "/parBlogList",
                            "yuzu-path": "/content/rows[1]/items[0]/blogs"
                        },
                        "_ref": "/parBlogArea",
                        "yuzu-path": "/content/rows[1]/items[0]"
                    }
                ]
            },
            {
                "config": {},
                "items": [
                    {
                        "item": {
                            "title": "Subscribe to our Newsletter",
                            "text": "Subscribe our newsletter gor get notification about new updates, etc...",
                            "form": {
                                "testForm": {
                                    "fieldsets": [
                                        {
                                            "fields": [
                                                {
                                                    "name": "email",
                                                    "label": "Your Email",
                                                    "value": "",
                                                    "type": "email",
                                                    "id": "",
                                                    "placeholder": "Your Email",
                                                    "pattern": "",
                                                    "autocomplete": "",
                                                    "min": "",
                                                    "max": "",
                                                    "minlength": "",
                                                    "maxlength": "",
                                                    "isRequired": true,
                                                    "isDisabled": false,
                                                    "isReadonly": false,
                                                    "_ref": "/parFormTextInput"
                                                }
                                            ]
                                        }
                                    ],
                                    "submitButtonText": "Subscribe",
                                    "_ref": "/parFormCta"
                                }
                            },
                            "_ref": "/parCtaForm",
                            "yuzu-path": "/content/rows[2]/items[0]/item"
                        },
                        "_ref": "/parCtaGridItem",
                        "yuzu-path": "/content/rows[2]/items[0]"
                    }
                ]
            }
        ]
    }
}